lightPollutionSimulation/__init__.py
lightPollutionSimulation/altitudeCalculation.py
lightPollutionSimulation/angleClass.py
lightPollutionSimulation/catalogBrowser.py
lightPollutionSimulation/celestialObject.py
lightPollutionSimulation/connector.py
lightPollutionSimulation/debugger.py
lightPollutionSimulation/lightIntensity.py
lightPollutionSimulation/lightPollutionMap.py
lightPollutionSimulation/lightPropagation.py
lightPollutionSimulation/main.py
lightPollutionSimulation/mapCoordinates.py
lightPollutionSimulation/plotAzimuth.py
lightPollutionSimulation/projection.py
lightPollutionSimulation/rayTracing.py
lightPollutionSimulation/skyClasses.py
lightpollutionsimulation-0.0.2.dist-info/METADATA
lightpollutionsimulation-0.0.2.dist-info/WHEEL
lightpollutionsimulation-0.0.2.dist-info/licenses/LICENSE
lightpollutionsimulation-0.0.2.dist-info/RECORD
