Metadata-Version: 2.4
Name: lightPollutionSimulation
Version: 0.0.2
Summary: Simulates the night sky brightness
Author: Thore Schoeller, Gerrit Erdt, Fabian Baeumer
License: CC BY-NC 4.0
License-File: LICENSE
Classifier: Operating System :: OS Independent
Classifier: Programming Language :: Python :: 3
Requires-Python: >=3.12
Requires-Dist: geopy
Requires-Dist: matplotlib
Requires-Dist: numba
Requires-Dist: numpy
Requires-Dist: psutil
Requires-Dist: rasterio
Provides-Extra: dev
Requires-Dist: pre-commit; extra == 'dev'
Requires-Dist: pytest; extra == 'dev'
